urlr/__init__.py
urlr/api_client.py
urlr/api_response.py
urlr/configuration.py
urlr/exceptions.py
urlr/py.typed
urlr/rest.py
urlr/api/__init__.py
urlr/api/access_tokens_api.py
urlr/api/domains_api.py
urlr/api/folders_api.py
urlr/api/links_api.py
urlr/api/qr_codes_api.py
urlr/api/statistics_api.py
urlr/api/workspaces_api.py
urlr/models/__init__.py
urlr/models/base_link_request.py
urlr/models/base_link_request_metatag.py
urlr/models/base_link_request_qrcode.py
urlr/models/create_access_token200_response.py
urlr/models/create_access_token401_response.py
urlr/models/create_access_token_request.py
urlr/models/create_domain200_response.py
urlr/models/create_domain_request.py
urlr/models/create_folder200_response.py
urlr/models/create_folder409_response.py
urlr/models/create_folder_request.py
urlr/models/create_link429_response.py
urlr/models/create_link_request.py
urlr/models/create_qr_code_request.py
urlr/models/create_qr_code_request_one_of.py
urlr/models/create_qr_code_request_one_of1.py
urlr/models/edit_link500_response.py
urlr/models/edit_link_request.py
urlr/models/get_folders200_response.py
urlr/models/get_folders200_response_folders_inner.py
urlr/models/get_link401_response.py
urlr/models/get_link404_response.py
urlr/models/get_link422_response.py
urlr/models/get_statistics200_response.py
urlr/models/get_statistics_request.py
urlr/models/get_teams200_response.py
urlr/models/get_teams200_response_teams_inner.py
urlr/models/link.py
urlr/models/link_geolinks_inner.py
urlr/models/link_geolinks_inner_conditions_inner.py
urlr/models/link_metatag.py
urlr/models/link_qrcode.py
urlr/models/link_tags_inner.py
urlr/models/link_utm.py
urlr/models/list_links200_response.py
urlr/models/refresh_access_token401_response.py
urlr/models/refresh_access_token_request.py
urlr-2.12.0.dist-info/METADATA
urlr-2.12.0.dist-info/WHEEL
urlr-2.12.0.dist-info/top_level.txt
urlr-2.12.0.dist-info/RECORD
