Metadata-Version: 2.4
Name: urlr
Version: 2.12.0
Summary: Python client for URLR
Home-page: 
Author: URLR
Author-email: URLR <contact@urlr.me>
License: MIT
Project-URL: Repository, https://github.com/urlr/urlr-python
Keywords: link shortener,api,sdk,client
Requires-Python: >=3.9
Requires-Dist: urllib3<3.0.0,>=2.1.0
Requires-Dist: python-dateutil>=2.8.2
Requires-Dist: pydantic>=2
Requires-Dist: typing-extensions>=4.7.1
Dynamic: author
